api/__init__.py
api/app.py
api/models.py
api/tests.py
api/utils.py
api/views.py
epguides_api-1.0.1.dist-info/DESCRIPTION.rst
epguides_api-1.0.1.dist-info/METADATA
epguides_api-1.0.1.dist-info/metadata.json
epguides_api-1.0.1.dist-info/RECORD
epguides_api-1.0.1.dist-info/top_level.txt
epguides_api-1.0.1.dist-info/WHEEL
