Metadata-Version: 2.0
Name: epguides-api
Version: 1.0.1
Summary: API for epguides.com
Home-page: http://github.com/frecar/epguides-api
Author: Fredrik Carlsen
Author-email: fredrik@carlsen.io
License: MIT
Platform: UNKNOWN
Classifier: Programming Language :: Python
Classifier: Programming Language :: Python :: 2.7
Classifier: Topic :: Software Development :: Libraries :: Python Modules
Classifier: Framework :: Flask
Classifier: Environment :: Web Environment
Classifier: Operating System :: OS Independent
Classifier: Natural Language :: English
